written_number/__init__.py
written_number/__main__.py
Written_Persian_Number-0.0.1.dist-info/METADATA
Written_Persian_Number-0.0.1.dist-info/WHEEL
Written_Persian_Number-0.0.1.dist-info/top_level.txt
Written_Persian_Number-0.0.1.dist-info/RECORD
