Metadata-Version: 2.1
Name: Written-Persian-Number
Version: 0.0.1
Summary: brief description
Author: Paria Jabbari
Author-email: jabbaripariya@gmail.com
License: The Unlicense
Project-URL: Homepage, https://github.com/pypa/sampleproject
Project-URL: Issues, https://github.com/pypa/sampleproject/issues
Classifier: Programming Language :: Python :: 3
Classifier: Operating System :: OS Independent
Requires-Python: >=3.8
